{
  "飞行": {
    "desc": "具有飞行的生物只能被具有飞行和/或延势的生物阻挡。"
  },
  "精熟咒语": {
    "keyword": true
  },
  "灵技": {
    "desc": "每当你施放非生物咒语时，此生物得+1/+1直到回合结束。"
  },
  "蛮化": {
    "desc": "如果此永久物未蛮化，则在其上放置%n个+1/+1指示物且它蛮化。"
  },
  "敏捷": {
    "desc": "此生物受你操控时便能攻击与{T}。"
  },
  "铭勇": {
    "desc": "当此生物对任一牌手造成战斗伤害时，若它未铭勇，则在其上放置%n个+1/+1指示物且它已铭勇。"
  },
  "威慑": {
    "desc": "具威慑异能的生物只能被两个或更多生物阻挡。"
  },
  "系命": {
    "desc": "此生物所造成的伤害会让你获得等量的生命。"
  },
  "延势": {
    "desc": "具有飞行的生物只能被具有飞行和/或延势的生物阻挡。"
  },
  "占卜": {
    "desc": "检视你牌库顶的%n张牌，将其中任意数量的牌以任意顺序置于你的牌库底，其余则以任意顺序置于你的牌库顶。"
  }
}
