{
  "不灭": {
    "desc": "注明「消灭」的效应不会消灭该永久物。伤害无法消灭具不灭异能的生物。"
  },
  "搭载": {
    "desc": "横置任意数量由你操控且力量总和等于或大于%0的未横置生物：此永久物成为神器生物直到回合结束。"
  },
  "飞行": {
    "desc": "具有飞行的生物只能被具有飞行和/或延势的生物阻挡。"
  },
  "警戒": {
    "desc": "具有警戒的生物攻击时不需横置。"
  },
  "激怒": {
    "keyword": true,
    "desc": "每当该生物受到伤害时，"
  },
  "精熟咒语": {
    "keyword": true,
    "desc": "如果你坟墓场中有两张或更多的瞬间和／或法术牌，"
  },
  "践踏": {
    "desc": "如果具践踏异能的生物将分配的伤害足以消灭所有阻挡它的生物，你可以将它所剩余数量的伤害分配给防御牌手或鹏洛客。"
  },
  "连击": {
    "desc": "具连击异能的生物能造成先攻与普通战斗伤害。"
  },
  "灵技": {
    "desc": "每当你施放非生物咒语时，此生物得+1/+1直到回合结束。"
  },
  "蛮化": {
    "desc": "如果此永久物未蛮化，则在其上放置%0个+1/+1指示物且它蛮化。"
  },
  "敏捷": {
    "desc": "具敏捷异能的生物受你操控时便能攻击与{T}。"
  },
  "铭勇": {
    "desc": "当具铭勇异能的生物对任一牌手造成战斗伤害时，若它未铭勇，则在其上放置%0个+1/+1指示物且它已铭勇。"
  },
  "装配": {
    "desc": "当此永久物进战场时，你可以在其上放置%0个+1/+1指示物。若你不如此作，则派出%0个1/1无色自动机衍生神器生物。"
  },
  "死触": {
    "desc": "具死触异能的生物对生物造成的任何数量伤害都足以消灭后者。"
  },
  "守军": {
    "desc": "具有守军异能的生物不能进行攻击。"
  },
  "神授": {
    "desc": "如果你支付此牌的神授费用来施放它，则它便是具「结附于生物」的灵气咒语。如果它未结附于生物上，就会再度成为生物。"
  },
  "闪现": {
    "desc": "你可以于你能够施放瞬间的时机下使用此牌。"
  },
  "突击": {
    "keyword": true,
    "desc": "，若你于本回合中曾以生物攻击，"
  },
  "先攻": {
    "desc": "具先攻异能的生物会比不具先攻异能的生物提前造成战斗伤害。"
  },
  "献力": {
    "desc": "由你操控之永久物的法术力费用当中每含有一个%0，你的该颜色献力就加一。"
  },
  "威慑": {
    "desc": "具威慑异能的生物只能被两个或更多生物阻挡。"
  },
  "系命": {
    "desc": "具系命异能的生物所造成的伤害会让你获得等量的生命。"
  },
  "延势": {
    "desc": "具有飞行的生物只能被具有飞行和/或延势的生物阻挡。"
  },
  "占卜": {
    "desc": "检视你牌库顶的%0张牌，将其中任意数量的牌以任意顺序置于你的牌库底，其余则以任意顺序置于你的牌库顶。"
  }
}
